Metadata-Version: 2.1
Name: llamac2py
Version: 0.1.4
Summary: llamac2py is a Python package that provides a wrapper for running inference using the Llama-2 Transformer model. The package includes a C executable (run.c) from Karpathy's llama2.c that performs the inference, and the wrapper module (wrapper.py) allows easy integration of the C code into Python scripts.
Author: Adarsh Shirawalmath
License-File: LICENSE
